nemo2riva/__init__.py
nemo2riva/args.py
nemo2riva/artifacts.py
nemo2riva/convert.py
nemo2riva/cookbook.py
nemo2riva/schema.py
nemo2riva/cli/__init__.py
nemo2riva/cli/nemo2riva.py
nemo2riva/patches/__init__.py
nemo2riva/patches/ctc.py
nemo2riva/patches/ctc_bpe.py
nemo2riva/patches/mtencdec.py
nemo2riva/patches/tts/__init__.py
nemo2riva/patches/tts/fastpitch.py
nemo2riva/patches/tts/general.py
nemo2riva/patches/tts/radtts.py
nemo2riva/validation_schemas/__init__.py
nemo2riva/validation_schemas/asr-scr-exported-encdecclsmodel.yaml
nemo2riva/validation_schemas/asr-stt-exported-encdecctcmodel.yaml
nemo2riva/validation_schemas/asr-stt-exported-encdectcmodelbpe.yaml
nemo2riva/validation_schemas/nlp-isc-exported-bert.yaml
nemo2riva/validation_schemas/nlp-mt-exported-encdecmtmodel.yaml
nemo2riva/validation_schemas/nlp-mt-exported-megatronnmtmodel.yaml
nemo2riva/validation_schemas/nlp-pc-exported-bert.yaml
nemo2riva/validation_schemas/nlp-qa-exported-bert.yaml
nemo2riva/validation_schemas/nlp-tc-exported-bert.yaml
nemo2riva/validation_schemas/nlp-tkc-exported-bert.yaml
nemo2riva/validation_schemas/tts-exported-fastpitchmodel.yaml
nemo2riva/validation_schemas/tts-exported-hifiganmodel.yaml
nemo2riva/validation_schemas/tts-exported-radttsmodel.yaml
nemo2riva-2.22.0.dist-info/licenses/LICENSE
nemo2riva-2.22.0.dist-info/METADATA
nemo2riva-2.22.0.dist-info/WHEEL
nemo2riva-2.22.0.dist-info/entry_points.txt
nemo2riva-2.22.0.dist-info/top_level.txt
nemo2riva-2.22.0.dist-info/RECORD
